mliiitl/__init__.py
mliiitl/mliiitl.py
mliiitl-3.5.0.dist-info/METADATA
mliiitl-3.5.0.dist-info/WHEEL
mliiitl-3.5.0.dist-info/top_level.txt
mliiitl-3.5.0.dist-info/RECORD
