Metadata-Version: 2.1
Name: mliiitl
Version: 3.5.0
Summary: A helping package for ML written by Sankalp
Home-page: https://github.com/Sankalp7943/optimisers-pypi-dev
Author: Sankalp Sharma
Author-email: sharma.sankalp97@gmail.com
License: UNKNOWN
Project-URL: Developer, https://sharmasankalp.com
Keywords: optimisers,machine learning,development
Platform: UNKNOWN
Classifier: Development Status :: 4 - Beta
Classifier: Intended Audience :: Developers
Classifier: License :: OSI Approved :: MIT License
Classifier: Programming Language :: Python :: 3
Classifier: Programming Language :: Python :: 3.6
Classifier: Programming Language :: Python :: 3.7
Classifier: Programming Language :: Python :: 3.8
Classifier: Programming Language :: Python :: 3.9
Classifier: Programming Language :: Python :: 3 :: Only
Requires-Python: >=3.6
Requires-Dist: numpy
Requires-Dist: pandas
Requires-Dist: matplotlib
Requires-Dist: keras
Requires-Dist: tensorflow-gpu
